llm_apm/__init__.py
llm_apm/config/settings.py
llm_apm/core/decorators.py
llm_apm/core/metrics.py
llm_apm/core/monitor.py
llm_apm/core/timer.py
llm_apm/exporters/prometheus.py
llm_apm/middleware/fastapi.py
llm_apm/storage/base.py
llm_apm/storage/postgresql_async.py
llm_apm/utils/cache.py
llm_apm/utils/cost_calculator.py
llm_apm/utils/prompt_utils.py
llm_apm/utils/quota.py
llm_apm/utils/sampler.py
llm_apm/utils/token_counter.py
llm_apm-1.2.3.dist-info/METADATA
llm_apm-1.2.3.dist-info/WHEEL
llm_apm-1.2.3.dist-info/top_level.txt
llm_apm-1.2.3.dist-info/RECORD
